xlref/__init__.py
xlref/_version.py
xlref/cli.py
xlref/errors.py
xlref/filters.py
xlref/parser.py
xlref/process.py
xlref-1.2.4.dist-info/AUTHORS.rst
xlref-1.2.4.dist-info/LICENSE.txt
xlref-1.2.4.dist-info/METADATA
xlref-1.2.4.dist-info/WHEEL
xlref-1.2.4.dist-info/entry_points.txt
xlref-1.2.4.dist-info/top_level.txt
xlref-1.2.4.dist-info/RECORD
