Metadata-Version: 2.1
Name: xlref
Version: 1.2.4
Summary: Excel table reader library.
Home-page: https://github.com/vinci1it2000/xlref
Download-URL: https://github.com/vinci1it2000/xlref/tarball/v1.2.4
Author: Vincenzo Arcidiacono
Author-email: vinci1it2000@gmail.com
License: EUPL 1.1+
Project-URL: Documentation, http://xlref.readthedocs.io
Project-URL: Issue tracker, https://github.com/vinci1it2000/xlref/issues
Project-URL: Donate, https://donorbox.org/xlref
Keywords: python,utility,library,data,scientific,range,engineering,data,excel,tables,reader,reference
Classifier: Programming Language :: Python
Classifier: Programming Language :: Python :: 3.6
Classifier: Programming Language :: Python :: 3.7
Classifier: Programming Language :: Python :: 3.8
Classifier: Programming Language :: Python :: 3.9
Classifier: Programming Language :: Python :: 3.10
Classifier: Programming Language :: Python :: 3.11
Classifier: Programming Language :: Python :: Implementation :: CPython
Classifier: Development Status :: 5 - Production/Stable
Classifier: Natural Language :: English
Classifier: Intended Audience :: Developers
Classifier: Intended Audience :: Science/Research
Classifier: License :: OSI Approved :: European Union Public Licence 1.1 (EUPL 1.1)
Classifier: Operating System :: MacOS :: MacOS X
Classifier: Operating System :: Microsoft :: Windows
Classifier: Operating System :: POSIX
Classifier: Operating System :: Unix
Classifier: Operating System :: OS Independent
Classifier: Topic :: Scientific/Engineering
Classifier: Topic :: Scientific/Engineering :: Information Analysis
Classifier: Topic :: Software Development :: Libraries :: Python Modules
Classifier: Topic :: Utilities
License-File: LICENSE.txt
License-File: AUTHORS.rst
Requires-Dist: click
Requires-Dist: click-log
Requires-Dist: schedula >=1.1.1
Requires-Dist: numpy
Requires-Dist: pandas
Requires-Dist: openpyxl
Requires-Dist: simplejson
Provides-Extra: dev
Requires-Dist: wheel ; extra == 'dev'
Requires-Dist: sphinx >=7.2 ; extra == 'dev'
Requires-Dist: gitchangelog ; extra == 'dev'
Requires-Dist: mako ; extra == 'dev'
Requires-Dist: sphinx-rtd-theme ; extra == 'dev'
Requires-Dist: setuptools >=36.0.1 ; extra == 'dev'
Requires-Dist: sphinxcontrib-restbuilder ; extra == 'dev'
Requires-Dist: coveralls ; extra == 'dev'
Requires-Dist: ddt ; extra == 'dev'
Requires-Dist: twine ; extra == 'dev'
Requires-Dist: sphinx-click ; extra == 'dev'
